Workbook

Sheet 📚 KPI Glossary
A1: Hotel Commercial KPIs — Definitions & Benchmarks | مصطلحات الأداء التجاري الفندقي
A2: KPI | B2: Full Name | C2: Formula | D2: Benchmark | E2: Why It Matters
A3: ADR | B3: Average Daily Rate | C3: Total Room Revenue ÷ Rooms Sold | D3: SAR 400–900 (Makkah) | E3: Measures pricing power — higher ADR = stronger brand positioning
A4: Occupancy % | B4: Occupancy Rate | C4: Rooms Sold ÷ Rooms Available × 100 | D4: 65–85% | E4: Core demand indicator — how full the hotel is
A5: RevPAR | B5: Revenue Per Available Room | C5: Occupancy% × ADR OR Room Revenue ÷ Available Rooms | D5: SAR 280–720 | E5: The #1 commercial KPI — combines price AND volume in one number
A6: GOPPAR | B6: Gross Operating Profit Per Available Room | C6: Gross Operating Profit ÷ Total Available Rooms | D6: SAR 120–350 | E6: Measures true profitability — includes all departments not just rooms
A7: TRevPAR | B7: Total Revenue Per Available Room | C7: Total Revenue ÷ Available Rooms | D7: SAR 350–900 | E7: Captures non-room revenue (F&B, spa, events)
A8: NPS | B8: Net Promoter Score | C8: % Promoters (9–10) − % Detractors (0–6) | D8: 50–70 (Good) | E8: Predicts future bookings — satisfied guest returns and brings others
A9: F&B Cost % | B9: Food & Beverage Cost Ratio | C9: F&B Cost ÷ F&B Revenue × 100 | D9: 28–32% | E9: Key profitability lever — every 1% saved = significant margin gain
A10: Labor Cost % | B10: Labor Cost Ratio | C10: Staff Cost ÷ Total Revenue × 100 | D10: 28–35% | E10: Largest cost driver in hotels — must balance service quality vs efficiency
A11: CPOR | B11: Cost Per Occupied Room | C11: Total Operating Costs ÷ Rooms Occupied | D11: SAR 180–350 | E11: Operational efficiency — lower = leaner operations
A12: Market Penetration Index | B12: MPI / RGI | C12: Hotel Occupancy ÷ CompSet Occupancy × 100 | D12: Above 100 = winning | E12: Competitive positioning — are we capturing more than our fair share?
A13: Channel Mix | B13: Direct vs OTA | C13: Direct Bookings ÷ Total Bookings × 100 | D13: Direct > 40% | E13: Direct bookings = higher margin (no OTA commission 15–25%)
A14: GOP Margin | B14: Gross Operating Profit Margin | C14: GOP ÷ Total Revenue × 100 | D14: 30–45% | E14: Bottom-line health of the hotel operation

Sheet 📊 Monthly Data
A1: Elaf Group — Monthly Commercial Performance 2023–2024
A2: Hotel | B2: City | C2: Rooms | D2: Month | E2: Year | F2: Season | G2: Occupancy% | H2: ADR (SAR) | I2: RevPAR (SAR) | J2: Room Revenue | K2: F&B Revenue | L2: GOP | M2: Total Revenue | N2: Room Nights | O2: NPS Score | P2: Labor Cost% | Q2: F&B Cost% | R2: GOPPAR | S2: TRevPAR
A3: Elaf Makkah | B3: Makkah | C3: 500 | D3: Jan | E3: 2023 | F3: Regular | G3: 0.522 | H3: 431 | I3: 225 | J3: 3375767 | K3: 846378 | L3: 1550842 | M3: 4222145 | N3: 7830 | O3: 70.5 | P3: 0.288 | Q3: 0.277 | R3: 103.4 | S3: 281.5
A4: Elaf Makkah | B4: Makkah | C4: 500 | D4: Feb | E4: 2023 | F4: Umrah/Ramadan | G4: 0.531 | H4: 436 | I4: 232 | J4: 3472998 | K4: 963645 | L4: 1427917 | M4: 4436643 | N4: 7967 | O4: 48.4 | P4: 0.323 | Q4: 0.303 | R4: 95.2 | S4: 295.8
A5: Elaf Makkah | B5: Makkah | C5: 500 | D5: Mar | E5: 2023 | F5: Umrah/Ramadan | G5: 0.797 | H5: 671 | I5: 534 | J5: 8014816 | K5: 1663580 | L5: 3639595 | M5: 9678397 | N5: 11950 | O5: 63.1 | P5: 0.351 | Q5: 0.33 | R5: 242.6 | S5: 645.2
A6: Elaf Makkah | B6: Makkah | C6: 500 | D6: Apr | E6: 2023 | F6: Regular | G6: 0.561 | H6: 451 | I6: 253 | J6: 3798598 | K6: 997745 | L6: 1983108 | M6: 4796343 | N6: 8417 | O6: 52.9 | P6: 0.294 | Q6: 0.297 | R6: 132.2 | S6: 319.8
A7: Elaf Makkah | B7: Makkah | C7: 500 | D7: May | E7: 2023 | F7: Regular | G7: 0.536 | H7: 426 | I7: 228 | J7: 3425717 | K7: 725223 | L7: 1441318 | M7: 4150940 | N7: 8037 | O7: 61.9 | P7: 0.283 | Q7: 0.283 | R7: 96.1 | S7: 276.7
A8: Elaf Makkah | B8: Makkah | C8: 500 | D8: Jun | E8: 2023 | F8: Hajj | G8: 0.97 | H8: 848 | I8: 823 | J8: 12342814 | K8: 2874524 | L8: 4736788 | M8: 15217338 | N8: 14550 | O8: 43.4 | P8: 0.324 | Q8: 0.287 | R8: 315.8 | S8: 1014.5
A9: Elaf Makkah | B9: Makkah | C9: 500 | D9: Jul | E9: 2023 | F9: Hajj | G9: 0.97 | H9: 829 | I9: 804 | J9: 12065098 | K9: 3566987 | L9: 5304071 | M9: 15632085 | N9: 14550 | O9: 54.7 | P9: 0.316 | Q9: 0.288 | R9: 353.6 | S9: 1042.1
A10: Elaf Makkah | B10: Makkah | C10: 500 | D10: Aug | E10: 2023 | F10: Regular | G10: 0.569 | H10: 489 | I10: 278 | J10: 4174486 | K10: 1095763 | L10: 2036461 | M10: 5270249 | N10: 8533 | O10: 74.8 | P10: 0.358 | Q10: 0.316 | R10: 135.8 | S10: 351.3
A11: Elaf Makkah | B11: Makkah | C11: 500 | D11: Sep | E11: 2023 | F11: Regular | G11: 0.576 | H11: 483 | I11: 278 | J11: 4176720 | K11: 1151155 | L11: 1864139 | M11: 5327875 | N11: 8640 | O11: 58.5 | P11: 0.345 | Q11: 0.307 | R11: 124.3 | S11: 355.2
A12: Elaf Makkah | B12: Makkah | C12: 500 | D12: Oct | E12: 2023 | F12: Regular | G12: 0.604 | H12: 516 | I12: 311 | J12: 4670948 | K12: 1091418 | L12: 1989427 | M12: 5762366 | N12: 9054 | O12: 63 | P12: 0.323 | Q12: 0.271 | R12: 132.6 | S12: 384.2
A13: Elaf Makkah | B13: Makkah | C13: 500 | D13: Nov | E13: 2023 | F13: Regular | G13: 0.575 | H13: 473 | I13: 272 | J13: 4079058 | K13: 1192745 | L13: 1887271 | M13: 5271802 | N13: 8626 | O13: 69.3 | P13: 0.338 | Q13: 0.298 | R13: 125.8 | S13: 351.5
A14: Elaf Makkah | B14: Makkah | C14: 500 | D14: Dec | E14: 2023 | F14: Regular | G14: 0.654 | H14: 524 | I14: 342 | J14: 5135465 | K14: 1523192 | L14: 2750434 | M14: 6658657 | N14: 9808 | O14: 66 | P14: 0.352 | Q14: 0.278 | R14: 183.4 | S14: 443.9
... A218: Elaf Al-Saqriya | B218: Makkah | C218: 380 | D218: Dec | E218: 2024 | F218: Regular | G218: 0.732 | H218: 669 | I218: 490 | J218: 5581641 | K218: 1497006 | L218: 2860898 | M218: 7078647 | N218: 8342 | O218: 57 | P218: 0.292 | Q218: 0.317 | R218: 251 | S218: 620.9

Sheet 🏨 Hotel Summary
A1: Hotel Performance Summary 2024 — All KPIs | ملخص الأداء التجاري
A2: Hotel | B2: City | C2: Rooms | D2: Avg Occupancy | E2: Avg ADR | F2: RevPAR | G2: GOPPAR | H2: TRevPAR | I2: Avg NPS | J2: Labor Cost% | K2: Rating
A3: Elaf Makkah | B3: Makkah | C3: 500 | D3: =AVERAGEIFS('📊 Monthly Data'!G:G,'📊 Monthly Data'!A:A,A3,'📊 Monthly Data'!E:E,2024) -> 0.71641667 | E3: =AVERAGEIFS('📊 Monthly Data'!H:H,'📊 Monthly Data'!A:A,A3,'📊 Monthly Data'!E:E,2024) -> 599 | F3: =AVERAGEIFS('📊 Monthly Data'!I:I,'📊 Monthly Data'!A:A,A3,'📊 Monthly Data'!E:E,2024) -> 452.16667 | G3: =AVERAGEIFS('📊 Monthly Data'!R:R,'📊 Monthly Data'!A:A,A3,'📊 Monthly Data'!E:E,2024) -> 211.58333 | H3: =AVERAGEIFS('📊 Monthly Data'!S:S,'📊 Monthly Data'!A:A,A3,'📊 Monthly Data'!E:E,2024) -> 572.93333 | I3: =AVERAGEIFS('📊 Monthly Data'!O:O,'📊 Monthly Data'!A:A,A3,'📊 Monthly Data'!E:E,2024) -> 59.4 | J3: =AVERAGEIFS('📊 Monthly Data'!P:P,'📊 Monthly Data'!A:A,A3,'📊 Monthly Data'!E:E,2024) -> 0.32616667 | K3: =IF(D3>=0.82,"⭐⭐⭐ Strong",IF(D3>=0.68,"⭐⭐ Average","⭐ Needs Focus")) -> ⭐⭐ Average
A4: Elaf Ajyad | B4: Makkah | C4: 320 | D4: =AVERAGEIFS('📊 Monthly Data'!G:G,'📊 Monthly Data'!A:A,A4,'📊 Monthly Data'!E:E,2024) -> 0.74191667 | E4: =AVERAGEIFS('📊 Monthly Data'!H:H,'📊 Monthly Data'!A:A,A4,'📊 Monthly Data'!E:E,2024) -> 804.5 | F4: =AVERAGEIFS('📊 Monthly Data'!I:I,'📊 Monthly Data'!A:A,A4,'📊 Monthly Data'!E:E,2024) -> 627.16667 | G4: =AVERAGEIFS('📊 Monthly Data'!R:R,'📊 Monthly Data'!A:A,A4,'📊 Monthly Data'!E:E,2024) -> 278.54167 | H4: =AVERAGEIFS('📊 Monthly Data'!S:S,'📊 Monthly Data'!A:A,A4,'📊 Monthly Data'!E:E,2024) -> 780.06667 | I4: =AVERAGEIFS('📊 Monthly Data'!O:O,'📊 Monthly Data'!A:A,A4,'📊 Monthly Data'!E:E,2024) -> 58.05 | J4: =AVERAGEIFS('📊 Monthly Data'!P:P,'📊 Monthly Data'!A:A,A4,'📊 Monthly Data'!E:E,2024) -> 0.32616667 | K4: =IF(D4>=0.82,"⭐⭐⭐ Strong",IF(D4>=0.68,"⭐⭐ Average","⭐ Needs Focus")) -> ⭐⭐ Average
A5: Elaf Mashaer | B5: Makkah | C5: 280 | D5: =AVERAGEIFS('📊 Monthly Data'!G:G,'📊 Monthly Data'!A:A,A5,'📊 Monthly Data'!E:E,2024) -> 0.7075 | E5: =AVERAGEIFS('📊 Monthly Data'!H:H,'📊 Monthly Data'!A:A,A5,'📊 Monthly Data'!E:E,2024) -> 826 | F5: =AVERAGEIFS('📊 Monthly Data'!I:I,'📊 Monthly Data'!A:A,A5,'📊 Monthly Data'!E:E,2024) -> 613.83333 | G5: =AVERAGEIFS('📊 Monthly Data'!R:R,'📊 Monthly Data'!A:A,A5,'📊 Monthly Data'!E:E,2024) -> 282.425 | H5: =AVERAGEIFS('📊 Monthly Data'!S:S,'📊 Monthly Data'!A:A,A5,'📊 Monthly Data'!E:E,2024) -> 764.43333 | I5: =AVERAGEIFS('📊 Monthly Data'!O:O,'📊 Monthly Data'!A:A,A5,'📊 Monthly Data'!E:E,2024) -> 64.258333 | J5: =AVERAGEIFS('📊 Monthly Data'!P:P,'📊 Monthly Data'!A:A,A5,'📊 Monthly Data'!E:E,2024) -> 0.32325 | K5: =IF(D5>=0.82,"⭐⭐⭐ Strong",IF(D5>=0.68,"⭐⭐ Average","⭐ Needs Focus")) -> ⭐⭐ Average
A6: Elaf Taiba | B6: Makkah | C6: 420 | D6: =AVERAGEIFS('📊 Monthly Data'!G:G,'📊 Monthly Data'!A:A,A6,'📊 Monthly Data'!E:E,2024) -> 0.766 | E6: =AVERAGEIFS('📊 Monthly Data'!H:H,'📊 Monthly Data'!A:A,A6,'📊 Monthly Data'!E:E,2024) -> 829.58333 | F6: =AVERAGEIFS('📊 Monthly Data'!I:I,'📊 Monthly Data'!A:A,A6,'📊 Monthly Data'!E:E,2024) -> 661.91667 | G6: =AVERAGEIFS('📊 Monthly Data'!R:R,'📊 Monthly Data'!A:A,A6,'📊 Monthly Data'!E:E,2024) -> 298.44167 | H6: =AVERAGEIFS('📊 Monthly Data'!S:S,'📊 Monthly Data'!A:A,A6,'📊 Monthly Data'!E:E,2024) -> 833.16667 | I6: =AVERAGEIFS('📊 Monthly Data'!O:O,'📊 Monthly Data'!A:A,A6,'📊 Monthly Data'!E:E,2024) -> 56.816667 | J6: =AVERAGEIFS('📊 Monthly Data'!P:P,'📊 Monthly Data'!A:A,A6,'📊 Monthly Data'!E:E,2024) -> 0.32116667 | K6: =IF(D6>=0.82,"⭐⭐⭐ Strong",IF(D6>=0.68,"⭐⭐ Average","⭐ Needs Focus")) -> ⭐⭐ Average
A7: Elaf Kinda | B7: Makkah | C7: 350 | D7: =AVERAGEIFS('📊 Monthly Data'!G:G,'📊 Monthly Data'!A:A,A7,'📊 Monthly Data'!E:E,2024) -> 0.73358333 | E7: =AVERAGEIFS('📊 Monthly Data'!H:H,'📊 Monthly Data'!A:A,A7,'📊 Monthly Data'!E:E,2024) -> 758.08333 | F7: =AVERAGEIFS('📊 Monthly Data'!I:I,'📊 Monthly Data'!A:A,A7,'📊 Monthly Data'!E:E,2024) -> 583.58333 | G7: =AVERAGEIFS('📊 Monthly Data'!R:R,'📊 Monthly Data'!A:A,A7,'📊 Monthly Data'!E:E,2024) -> 269.78333 | H7: =AVERAGEIFS('📊 Monthly Data'!S:S,'📊 Monthly Data'!A:A,A7,'📊 Monthly Data'!E:E,2024) -> 732.91667 | I7: =AVERAGEIFS('📊 Monthly Data'!O:O,'📊 Monthly Data'!A:A,A7,'📊 Monthly Data'!E:E,2024) -> 62.625 | J7: =AVERAGEIFS('📊 Monthly Data'!P:P,'📊 Monthly Data'!A:A,A7,'📊 Monthly Data'!E:E,2024) -> 0.32316667 | K7: =IF(D7>=0.82,"⭐⭐⭐ Strong",IF(D7>=0.68,"⭐⭐ Average","⭐ Needs Focus")) -> ⭐⭐ Average
A8: Elaf Bakkah | B8: Makkah | C8: 300 | D8: =AVERAGEIFS('📊 Monthly Data'!G:G,'📊 Monthly Data'!A:A,A8,'📊 Monthly Data'!E:E,2024) -> 0.70808333 | E8: =AVERAGEIFS('📊 Monthly Data'!H:H,'📊 Monthly Data'!A:A,A8,'📊 Monthly Data'!E:E,2024) -> 696.66667 | F8: =AVERAGEIFS('📊 Monthly Data'!I:I,'📊 Monthly Data'!A:A,A8,'📊 Monthly Data'!E:E,2024) -> 521 | G8: =AVERAGEIFS('📊 Monthly Data'!R:R,'📊 Monthly Data'!A:A,A8,'📊 Monthly Data'!E:E,2024) -> 236.58333 | H8: =AVERAGEIFS('📊 Monthly Data'!S:S,'📊 Monthly Data'!A:A,A8,'📊 Monthly Data'!E:E,2024) -> 653.91667 | I8: =AVERAGEIFS('📊 Monthly Data'!O:O,'📊 Monthly Data'!A:A,A8,'📊 Monthly Data'!E:E,2024) -> 62.65 | J8: =AVERAGEIFS('📊 Monthly Data'!P:P,'📊 Monthly Data'!A:A,A8,'📊 Monthly Data'!E:E,2024) -> 0.31516667 | K8: =IF(D8>=0.82,"⭐⭐⭐ Strong",IF(D8>=0.68,"⭐⭐ Average","⭐ Needs Focus")) -> ⭐⭐ Average
A9: Joadian Red Sea | B9: Jeddah | C9: 250 | D9: =AVERAGEIFS('📊 Monthly Data'!G:G,'📊 Monthly Data'!A:A,A9,'📊 Monthly Data'!E:E,2024) -> 0.78016667 | E9: =AVERAGEIFS('📊 Monthly Data'!H:H,'📊 Monthly Data'!A:A,A9,'📊 Monthly Data'!E:E,2024) -> 509.33333 | F9: =AVERAGEIFS('📊 Monthly Data'!I:I,'📊 Monthly Data'!A:A,A9,'📊 Monthly Data'!E:E,2024) -> 411.58333 | G9: =AVERAGEIFS('📊 Monthly Data'!R:R,'📊 Monthly Data'!A:A,A9,'📊 Monthly Data'!E:E,2024) -> 188.01667 | H9: =AVERAGEIFS('📊 Monthly Data'!S:S,'📊 Monthly Data'!A:A,A9,'📊 Monthly Data'!E:E,2024) -> 513.24167 | I9: =AVERAGEIFS('📊 Monthly Data'!O:O,'📊 Monthly Data'!A:A,A9,'📊 Monthly Data'!E:E,2024) -> 63.858333 | J9: =AVERAGEIFS('📊 Monthly Data'!P:P,'📊 Monthly Data'!A:A,A9,'📊 Monthly Data'!E:E,2024) -> 0.31883333 | K9: =IF(D9>=0.82,"⭐⭐⭐ Strong",IF(D9>=0.68,"⭐⭐ Average","⭐ Needs Focus")) -> ⭐⭐ Average
A10: Joadian Olaya | B10: Riyadh | C10: 280 | D10: =AVERAGEIFS('📊 Monthly Data'!G:G,'📊 Monthly Data'!A:A,A10,'📊 Monthly Data'!E:E,2024) -> 0.75983333 | E10: =AVERAGEIFS('📊 Monthly Data'!H:H,'📊 Monthly Data'!A:A,A10,'📊 Monthly Data'!E:E,2024) -> 587 | F10: =AVERAGEIFS('📊 Monthly Data'!I:I,'📊 Monthly Data'!A:A,A10,'📊 Monthly Data'!E:E,2024) -> 466.08333 | G10: =AVERAGEIFS('📊 Monthly Data'!R:R,'📊 Monthly Data'!A:A,A10,'📊 Monthly Data'!E:E,2024) -> 210.95833 | H10: =AVERAGEIFS('📊 Monthly Data'!S:S,'📊 Monthly Data'!A:A,A10,'📊 Monthly Data'!E:E,2024) -> 583.49167 | I10: =AVERAGEIFS('📊 Monthly Data'!O:O,'📊 Monthly Data'!A:A,A10,'📊 Monthly Data'!E:E,2024) -> 58.583333 | J10: =AVERAGEIFS('📊 Monthly Data'!P:P,'📊 Monthly Data'!A:A,A10,'📊 Monthly Data'!E:E,2024) -> 0.31108333 | K10: =IF(D10>=0.82,"⭐⭐⭐ Strong",IF(D10>=0.68,"⭐⭐ Average","⭐ Needs Focus")) -> ⭐⭐ Average
A11: Elaf Al-Saqriya | B11: Makkah | C11: 380 | D11: =AVERAGEIFS('📊 Monthly Data'!G:G,'📊 Monthly Data'!A:A,A11,'📊 Monthly Data'!E:E,2024) -> 0.7525 | E11: =AVERAGEIFS('📊 Monthly Data'!H:H,'📊 Monthly Data'!A:A,A11,'📊 Monthly Data'!E:E,2024) -> 739.58333 | F11: =AVERAGEIFS('📊 Monthly Data'!I:I,'📊 Monthly Data'!A:A,A11,'📊 Monthly Data'!E:E,2024) -> 581.16667 | G11: =AVERAGEIFS('📊 Monthly Data'!R:R,'📊 Monthly Data'!A:A,A11,'📊 Monthly Data'!E:E,2024) -> 264.23333 | H11: =AVERAGEIFS('📊 Monthly Data'!S:S,'📊 Monthly Data'!A:A,A11,'📊 Monthly Data'!E:E,2024) -> 728.48333 | I11: =AVERAGEIFS('📊 Monthly Data'!O:O,'📊 Monthly Data'!A:A,A11,'📊 Monthly Data'!E:E,2024) -> 58.183333 | J11: =AVERAGEIFS('📊 Monthly Data'!P:P,'📊 Monthly Data'!A:A,A11,'📊 Monthly Data'!E:E,2024) -> 0.31041667 | K11: =IF(D11>=0.82,"⭐⭐⭐ Strong",IF(D11>=0.68,"⭐⭐ Average","⭐ Needs Focus")) -> ⭐⭐ Average

Sheet 📅 Seasonal Analysis
A1: Seasonal Commercial Analysis — Hajj vs Umrah vs Regular | تحليل الأداء الموسمي
A2: Season | B2: Avg Occupancy | C2: Avg ADR | D2: Avg RevPAR | E2: Avg GOPPAR | F2: Avg NPS | G2: Total Revenue | H2: Strategic Action
A3: Hajj | B3: =AVERAGEIF('📊 Monthly Data'!F:F,A3,'📊 Monthly Data'!G:G) -> 0.97 | C3: =AVERAGEIF('📊 Monthly Data'!F:F,A3,'📊 Monthly Data'!H:H) -> 1052.8889 | D3: =AVERAGEIF('📊 Monthly Data'!F:F,A3,'📊 Monthly Data'!I:I) -> 1021.3889 | E3: =AVERAGEIF('📊 Monthly Data'!F:F,A3,'📊 Monthly Data'!R:R) -> 457.73611 | F3: =AVERAGEIF('📊 Monthly Data'!F:F,A3,'📊 Monthly Data'!O:O) -> 50.997222 | G3: =SUMIF('📊 Monthly Data'!F:F,A3,'📊 Monthly Data'!M:M) -> 476949478 | H3: Dynamic pricing + yield management — maximize ADR, close low-rate channels
A4: Umrah/Ramadan | B4: =AVERAGEIF('📊 Monthly Data'!F:F,A4,'📊 Monthly Data'!G:G) -> 0.76608333 | C4: =AVERAGEIF('📊 Monthly Data'!F:F,A4,'📊 Monthly Data'!H:H) -> 692.58333 | D4: =AVERAGEIF('📊 Monthly Data'!F:F,A4,'📊 Monthly Data'!I:I) -> 552.52778 | E4: =AVERAGEIF('📊 Monthly Data'!F:F,A4,'📊 Monthly Data'!R:R) -> 247.34167 | F4: =AVERAGEIF('📊 Monthly Data'!F:F,A4,'📊 Monthly Data'!O:O) -> 63.008333 | G4: =SUMIF('📊 Monthly Data'!F:F,A4,'📊 Monthly Data'!M:M) -> 255829166 | H4: Package deals + group bookings — bundle rooms with F&B and transport
A5: Regular | B5: =AVERAGEIF('📊 Monthly Data'!F:F,A5,'📊 Monthly Data'!G:G) -> 0.64227778 | C5: =AVERAGEIF('📊 Monthly Data'!F:F,A5,'📊 Monthly Data'!H:H) -> 581.17361 | D5: =AVERAGEIF('📊 Monthly Data'!F:F,A5,'📊 Monthly Data'!I:I) -> 374.79861 | E5: =AVERAGEIF('📊 Monthly Data'!F:F,A5,'📊 Monthly Data'!R:R) -> 172.53125 | F5: =AVERAGEIF('📊 Monthly Data'!F:F,A5,'📊 Monthly Data'!O:O) -> 61.979167 | G5: =SUMIF('📊 Monthly Data'!F:F,A5,'📊 Monthly Data'!M:M) -> 695855072 | H5: Promotional rates + loyalty + corporate contracts — build base demand

Sheet 📈 Pareto Analysis
A1: Pareto Analysis — Which Hotels Drive 80% of Revenue? | تحليل باريتو للإيرادات
A2: Rank | B2: Hotel | C2: 2024 Revenue (SAR) | D2: Revenue Share % | E2: Cumulative % | F2: Pareto Zone | G2: Action
A3: 1 | B3: Elaf Makkah | C3: 195000000 | D3: 0.20123839 | E3: 0.20123839 | F3: 🟢 Core — Top 20% | G3: Protect & invest — these are your revenue engines
A4: 2 | B4: Elaf Ajyad | C4: 148000000 | D4: 0.15273478 | E4: 0.35397317 | F4: 🟢 Core — Top 20% | G4: Protect & invest — these are your revenue engines
A5: 3 | B5: Elaf Mashaer | C5: 132000000 | D5: 0.13622291 | E5: 0.49019608 | F5: 🟢 Core — Top 20% | G5: Protect & invest — these are your revenue engines
A6: 4 | B6: Elaf Taiba | C6: 122000000 | D6: 0.12590299 | E6: 0.61609907 | F6: 🟢 Core — Top 20% | G6: Protect & invest — these are your revenue engines
A7: 5 | B7: Elaf Kinda | C7: 98000000 | D7: 0.10113519 | E7: 0.71723426 | F7: 🟢 Core — Top 20% | G7: Protect & invest — these are your revenue engines
A8: 6 | B8: Elaf Bakkah | C8: 90000000 | D8: 0.092879257 | E8: 0.81011352 | F8: 🟢 Core — Top 20% | G8: Protect & invest — these are your revenue engines
A9: 7 | B9: Joadian Red Sea | C9: 74000000 | D9: 0.076367389 | E9: 0.88648091 | F9: 🟡 Growth Potential | G9: Optimize costs & grow occupancy
A10: 8 | B10: Joadian Olaya | C10: 66000000 | D10: 0.068111455 | E10: 0.95459236 | F10: 🟡 Growth Potential | G10: Optimize costs & grow occupancy
A11: 9 | B11: Elaf Al-Saqriya | C11: 44000000 | D11: 0.045407637 | E11: 1 | F11: 🟡 Growth Potential | G11: Optimize costs & grow occupancy

Sheet 🔧 Power BI Build Guide
A1: Power BI Dashboard Build Guide — Step by Step | دليل بناء الداشبورد خطوة بخطوة
A2: Step | B2: Action | C2: Details
A3: 1 | B3: Import Data | C3: Power BI → Get Data → Excel → Select this file → Load all sheets EXCEPT this guide
A4: 2 | B4: Build Relationships | C4: 📊 Monthly Data[Hotel] → 🏨 Hotel Summary[Hotel] | 📊 Monthly Data[Season] → 📅 Seasonal[Season]
A5: 3 | B5: Create DAX Measures | C5: Avg RevPAR = AVERAGE([RevPAR (SAR)]) Avg Occupancy = AVERAGE([Occupancy%]) Total Revenue = SUM([Total Revenue]) Avg GOPPAR = AVERAGE([GOPPAR]) YoY RevPAR Growth = DIVIDE([RevPAR 2024]-[RevPAR 2023],[RevPAR 2023])
A6: 4 | B6: Page 1 — Executive Overview | C6: KPI Cards (top row): Total Revenue | Avg RevPAR | Avg Occupancy | Avg GOPPAR | Avg NPS Bar Chart: Revenue by Hotel (sorted desc) Line Chart: Monthly RevPAR trend Slicer: Year
A7: 5 | B7: Page 2 — Commercial Deep Dive | C7: Clustered Bar: ADR vs RevPAR by Hotel Column: Occupancy by Season Scatter: ADR vs NPS (relationship) Slicer: Hotel + Year
A8: 6 | B8: Page 3 — Seasonal Performance | C8: 3 KPI cards per season (Hajj / Umrah / Regular) Line: Monthly Occupancy all 12 months Bar: RevPAR by Month with avg reference line Color code: Red=Hajj, Yellow=Umrah, Blue=Regular
A9: 7 | B9: Page 4 — Pareto & Profitability | C9: Bar + Line combo chart: Revenue bars + Cumulative % line Add 80% reference line → shows which hotels are the core GOPPAR gauge per hotel F&B Cost% vs Labor Cost% scatter
A10: 8 | B10: Page 5 — NPS & Quality | C10: NPS gauge (0–100 scale) Line: NPS trend by month Bar: NPS by Season (Hajj NPS drops — key insight) Scatter: NPS vs RevPAR (quality drives revenue)
A11: 9 | B11: Design Theme | C11: Primary: #1F4E79 (dark blue) Accent: #1D6F7A (teal) Warning: #C7A84A (gold) Background: #F2F2F2 Font: Segoe UI or Arial
A12: 10 | B12: Key Insight to Present to CEO | C12: 3 hotels generate 62% of total revenue (Pareto) Hajj season drives 35% of annual revenue in 2 months NPS drops 15 points during peak season → quality investment needed GOPPAR gap between best/worst hotel = optimization opportunity
